VacuumFlask/__init__.py
VacuumFlask-0.0.1.dist-info/LICENSE
VacuumFlask-0.0.1.dist-info/METADATA
VacuumFlask-0.0.1.dist-info/WHEEL
VacuumFlask-0.0.1.dist-info/top_level.txt
VacuumFlask-0.0.1.dist-info/RECORD
