Metadata-Version: 2.1
Name: VacuumFlask
Version: 0.0.1
Summary: Flask validation for Sessions, Forms, URL Parameters, and Query Parameters
License: GNU GENERAL PUBLIC LICENSE
Project-URL: Homepage, https://github.com/jb2170/VacuumFlask/
License-File: LICENSE
Requires-Dist: flask
